odoo10_addon_base_maintenance_config-10.0.1.0.0.99.dev6-py2.7-nspkg.pth
odoo/addons/base_maintenance_config/README.rst
odoo/addons/base_maintenance_config/__init__.py
odoo/addons/base_maintenance_config/__manifest__.py
odoo/addons/base_maintenance_config/menuitems.xml
odoo/addons/base_maintenance_config/data/maintenance_data.xml
odoo/addons/base_maintenance_config/models/__init__.py
odoo/addons/base_maintenance_config/models/maintenance_config_settings.py
odoo/addons/base_maintenance_config/security/maintenance_security.xml
odoo/addons/base_maintenance_config/static/description/icon.png
odoo/addons/base_maintenance_config/views/maintenance_config_settings.xml
odoo10_addon_base_maintenance_config-10.0.1.0.0.99.dev6.dist-info/METADATA
odoo10_addon_base_maintenance_config-10.0.1.0.0.99.dev6.dist-info/RECORD
odoo10_addon_base_maintenance_config-10.0.1.0.0.99.dev6.dist-info/WHEEL
odoo10_addon_base_maintenance_config-10.0.1.0.0.99.dev6.dist-info/namespace_packages.txt
odoo10_addon_base_maintenance_config-10.0.1.0.0.99.dev6.dist-info/top_level.txt
